{
  "id": "rss-20260723-quality-non-fiction-books-are-the-antithesis-of-ai-slop",
  "title": "Quality non-fiction books are the antithesis of AI slop",
  "source": "rss",
  "source_url": "https://resobscura.substack.com/p/quality-non-fiction-books-are-the",
  "summary": "这篇文章探讨了高质量非虚构书籍与AI生成的低质量内容（AI slop）之间的对立关系。作者认为，AI生成的文本往往缺乏深度、准确性和原创性，而非虚构书籍则依赖于严谨的研究、事实核查和作者的专业知识。文章强调了在信息泛滥的时代，阅读和创作高质量非虚构作品的重要性，并指出AI工具虽然能辅助写作，但无法替代人类对复杂主题的深入理解和批判性思维。",
  "summary_en": "This article explores the antithesis between high-quality non-fiction books and AI-generated low-quality content (AI slop). The author argues that AI-generated text often lacks depth, accuracy, and originality, while non-fiction books rely on rigorous research, fact-checking, and the author's expertise. The article emphasizes the importance of reading and creating high-quality non-fiction works in an era of information overload, and points out that AI tools, while assisting writing, cannot replace human deep understanding and critical thinking on complex topics.",
  "tags": [
    "ai slop",
    "non-fiction",
    "content quality",
    "critical thinking",
    "information literacy"
  ],
  "status": "draft",
  "score": 1,
  "metrics": {
    "stars": 0
  },
  "fetched_at": "2026-07-23T10:13:10.769117+00:00",
  "analyzed_at": "2026-07-23T10:14:16.534548+00:00",
  "published_at": null
}